nestle.py
nestle-0.2.1.dist-info/licenses/LICENSE.md
nestle-0.2.1.dist-info/METADATA
nestle-0.2.1.dist-info/WHEEL
nestle-0.2.1.dist-info/top_level.txt
nestle-0.2.1.dist-info/RECORD
